dscaper/__init__.py
dscaper/audio.py
dscaper/core.py
dscaper/dscaper.py
dscaper/dscaper_datatypes.py
dscaper/scaper_exceptions.py
dscaper/scaper_warnings.py
dscaper/util.py
dscaper/version.py
dscaper-1.7.1.dist-info/licenses/LICENSE
dscaper-1.7.1.dist-info/METADATA
dscaper-1.7.1.dist-info/WHEEL
dscaper-1.7.1.dist-info/top_level.txt
dscaper-1.7.1.dist-info/RECORD
