Metadata-Version: 2.4
Name: dscaper
Version: 1.7.1
Summary: A library for soundscape synthesis and augmentation
Home-page: https://github.com/dscaper/dscaper
Download-URL: 
Author: Duncan MacConnell
Author-email: Justin Salamon <justin.salamon@gmail.com>, David Grünert <grud@zhaw.ch>
License: BSD-3-Clause
Project-URL: Homepage, https://github.com/dscaper/dscaper
Project-URL: Repository, https://github.com/dscaper/dscaper
Project-URL: Issues, https://github.com/dscaper/dscaper/issues
Keywords: audio,sound,soundscape,environmental,dsp,mixing
Classifier: License :: OSI Approved :: BSD License
Classifier: Programming Language :: Python
Classifier: Intended Audience :: Developers
Classifier: Intended Audience :: Science/Research
Classifier: Topic :: Multimedia :: Sound/Audio :: Analysis
Classifier: Topic :: Multimedia :: Sound/Audio :: Sound Synthesis
Classifier: Programming Language :: Python :: 3.12
Requires-Python: >=3.8
License-File: LICENSE
Requires-Dist: sox
Requires-Dist: soundfile
Requires-Dist: scipy
Requires-Dist: fastapi
Requires-Dist: jams
Requires-Dist: pyloudnorm
Provides-Extra: docs
Requires-Dist: sphinx; extra == "docs"
Requires-Dist: sphinx_rtd_theme; extra == "docs"
Requires-Dist: sphinx_issues; extra == "docs"
Provides-Extra: tests
Requires-Dist: backports.tempfile; extra == "tests"
Requires-Dist: pytest; extra == "tests"
Requires-Dist: pytest-cov; extra == "tests"
Requires-Dist: tqdm; extra == "tests"
Dynamic: home-page
Dynamic: license-file
